mlpj/__init__.py
mlpj/actions_looper.py
mlpj/ml_utils.py
mlpj/numpy_utils.py
mlpj/pandas_utils.py
mlpj/plot_utils.py
mlpj/project_utils.py
mlpj/python_utils.py
mlpj/result_display.py
mlpj/result_template.html
mlpj/stats_utils.py
mlpj/timeseries_utils.py
mlpj-0.3.0.dist-info/LICENSE
mlpj-0.3.0.dist-info/METADATA
mlpj-0.3.0.dist-info/WHEEL
mlpj-0.3.0.dist-info/top_level.txt
mlpj-0.3.0.dist-info/RECORD
