Metadata-Version: 2.1
Name: mlpj
Version: 0.3.0
Summary: Tools for machine learning projects
Home-page: https://github.com/bdanielby/mlpj
Author: Bruno Daniel
License: MIT
Project-URL: Homepage, https://github.com/bdanielby/mlpj
Project-URL: Source, https://github.com/bdanielby/mlpj
Classifier: Development Status :: 5 - Production/Stable
Classifier: Intended Audience :: Science/Research
Classifier: Intended Audience :: Information Technology
Classifier: Intended Audience :: Manufacturing
Classifier: License :: OSI Approved :: MIT License
Classifier: Operating System :: POSIX :: Linux
Classifier: Operating System :: MacOS
Classifier: Operating System :: Microsoft :: Windows
Classifier: Programming Language :: Python :: 3
License-File: LICENSE
Requires-Dist: numpy
Requires-Dist: pandas
Requires-Dist: matplotlib
Requires-Dist: numba
Requires-Dist: lockfile
Requires-Dist: jinja2
Requires-Dist: markupsafe
